{
  "EFFECTS": {
    "ballTrailHexaCold": [
      {
        "useTargetAngle": true,
        "keepAngleSync": false,
        "offset": {
          "x": 0,
          "y": 0,
          "z": 3
        },
        "pAlpha": {
          "init": 1,
          "end": {
            "value": 0,
            "spline": ""
          }
        },
        "pScale": {
          "init": {
            "x": 1,
            "y": 1
          },
          "start": {
            "value": {
              "x": 0.5,
              "y": 0.5
            },
            "spline": ""
          }
        },
        "particleDuration": 0.15,
        "anim": "HEXAGON_COLD",
        "type": "PLAY_ANIM"
      },
      {
        "time": 0.016,
        "type": "WAIT"
      }
    ],
    "ballTrailHexaColdSlow": [
      {
        "useTargetAngle": true,
        "keepAngleSync": false,
        "offset": {
          "x": 0,
          "y": 0,
          "z": 3
        },
        "pAlpha": {
          "init": 1,
          "end": {
            "value": 0,
            "spline": ""
          }
        },
        "pScale": {
          "init": {
            "x": 1,
            "y": 1
          },
          "start": {
            "value": {
              "x": 0.5,
              "y": 0.5
            },
            "spline": ""
          }
        },
        "particleDuration": 0.5,
        "anim": "HEXAGON_COLD",
        "type": "PLAY_ANIM"
      },
      {
        "time": 0.016,
        "type": "WAIT"
      }
    ],
    "hailBullet2Aura": [
      {
        "color": "#aaccff",
        "maxAlpha": 0.5,
        "minAlpha": 0,
        "blinkDuration": 0.1,
        "blinkCount": -1,
        "noLighter": true,
        "type": "BLINK_COLOR"
      },
      {
        "size": "L",
        "fadeIn": 0,
        "fadeOut": 0.1,
        "duration": -1,
        "glow": false,
        "type": "LIGHT"
      },
      {
        "type": "LOOP_START"
      },
      {
        "color": "white",
        "colorAlpha": "#00aaff",
        "noLighter": false,
        "pAlpha": {
          "init": 0.4,
          "start": {
            "value": 0,
            "spline": ""
          }
        },
        "pScale": {
          "init": {
            "x": 1,
            "y": 1
          },
          "start": {
            "value": {
              "x": 0.7,
              "y": 0.7
            },
            "spline": ""
          }
        },
        "offset": {
          "x": 0,
          "y": -3,
          "z": -3
        },
        "particleDuration": 0.15,
        "type": "COPY_SPRITE"
      },
      {
        "time": 0.03,
        "type": "WAIT"
      },
      {
        "color": "white",
        "colorAlpha": "#00aaff",
        "noLighter": false,
        "pAlpha": {
          "init": 0.4,
          "start": {
            "value": 0,
            "spline": ""
          }
        },
        "pScale": {
          "init": {
            "x": 1,
            "y": 1
          },
          "start": {
            "value": {
              "x": 0.7,
              "y": 0.7
            },
            "spline": ""
          }
        },
        "offset": {
          "x": 0,
          "y": -3,
          "z": -3
        },
        "particleDuration": 0.15,
        "type": "COPY_SPRITE"
      },
      {
        "numParticles": 1,
        "duration": 0.1,
        "centralAngle": 1,
        "random": true,
        "startDist": 4,
        "moveDist": 16,
        "moveVariance": 8,
        "keySpline": "EASE_OUT",
        "moveRotate": 0,
        "inverse": false,
        "collision": false,
        "pRotate": {
          "init": 0,
          "start": {
            "value": 0.2,
            "spline": ""
          }
        },
        "pScale": {
          "init": {
            "x": 0.8,
            "y": 0.8
          },
          "end": {
            "value": {
              "x": 0,
              "y": 0
            },
            "time": 0.2,
            "spline": ""
          }
        },
        "moveWithTarget": 0,
        "particleDuration": 0.6,
        "angleVary": 1,
        "cancelable": false,
        "anim": "SNOWFLAKE1",
        "type": "OFFSET_PARTICLE_CIRCLE"
      },
      {
        "time": 0.03,
        "type": "WAIT"
      },
      {
        "type": "LOOP_END"
      }
    ],
    "icicleExplodeSmallRumble": [
      {
        "volume": 1,
        "global": false,
        "loop": false,
        "sound": "media/sound/battle/enemies/mine/ground-ice-crystal-disintegrate.ogg",
        "type": "PLAY_SOUND"
      },
      {
        "rumbleType": "RANDOM",
        "power": "WEAK",
        "speed": "NORMAL",
        "duration": 0.1,
        "fade": false,
        "type": "RUMBLE"
      },
      {
        "size": "L",
        "fadeIn": 0,
        "fadeOut": 0.2,
        "duration": 0.2,
        "glow": true,
        "type": "LIGHT"
      },
      {
        "numParticles": 3,
        "duration": 0,
        "centralAngle": 1,
        "startDist": 4,
        "uniformRandom": 1,
        "moveDist": 8,
        "moveVariance": 4,
        "keySpline": "EASE_OUT",
        "inverse": false,
        "collision": false,
        "pScale": {
          "init": {
            "x": 1,
            "y": 1
          },
          "end": {
            "value": {
              "x": 0,
              "y": 0
            },
            "time": 0.2,
            "spline": ""
          }
        },
        "anim": "SNOW_BURST",
        "type": "OFFSET_PARTICLE_CIRCLE"
      },
      {
        "alpha": 0,
        "duration": 0.2,
        "type": "CHANGE_ALPHA"
      },
      {
        "numParticles": 2,
        "duration": 0,
        "centralAngle": 1,
        "startDist": 2,
        "uniformRandom": 0.6,
        "particleRotate": true,
        "offset": {
          "x": 0,
          "y": 0,
          "z": 0
        },
        "minSpeed": 10,
        "maxSpeed": 40,
        "minZSpeed": 180,
        "maxZSpeed": 220,
        "zBounciness": 0.5,
        "minZVel": 80,
        "collision": false,
        "pAlpha": {
          "init": 0.8,
          "end": {
            "value": 0,
            "time": 0.2,
            "spline": ""
          }
        },
        "pScale": {
          "init": {
            "x": 1,
            "y": 1
          },
          "end": {
            "value": {
              "x": 0,
              "y": 0
            },
            "time": 0.5,
            "spline": ""
          }
        },
        "pRotate": {
          "init": -0.5,
          "start": {
            "value": 0,
            "time": 1,
            "spline": ""
          }
        },
        "particleDuration": 0.8,
        "anim": "ICE_SHARD3",
        "type": "DEBRIS_CIRCLE"
      },
      {
        "numParticles": 1,
        "duration": 0,
        "centralAngle": 1,
        "startDist": 2,
        "uniformRandom": 0.6,
        "offset": {
          "x": 0,
          "y": 0,
          "z": 0
        },
        "minSpeed": 10,
        "maxSpeed": 40,
        "minZSpeed": 180,
        "maxZSpeed": 220,
        "zBounciness": 0.5,
        "minZVel": 80,
        "collision": false,
        "pAlpha": {
          "init": 0.8,
          "end": {
            "value": 0,
            "time": 0.2,
            "spline": ""
          }
        },
        "pScale": {
          "init": {
            "x": 1,
            "y": 1
          },
          "end": {
            "value": {
              "x": 0,
              "y": 0
            },
            "time": 0.5,
            "spline": ""
          }
        },
        "pRotate": {
          "init": -0.5,
          "start": {
            "value": 0,
            "time": 1,
            "spline": ""
          }
        },
        "particleDuration": 0.8,
        "anim": "ICE_SHARD6",
        "type": "DEBRIS_CIRCLE"
      }
    ]
  }
}