{
  "EFFECTS": {
    "shockCard1Death": [
      {
        "numParticles": 1,
        "duration": 0,
        "centralAngle": 1,
        "startDist": 0,
        "random": true,
        "zBounciness": 0,
        "collision": true,
        "angleVary": 1,
        "offset": {
          "x": 0,
          "y": 0,
          "z": 0
        },
        "minSpeed": 10,
        "maxSpeed": 30,
        "minZSpeed": 60,
        "maxZSpeed": 100,
        "minZVel": 20,
        "pAlpha": {
          "init": 0.8,
          "end": {
            "value": 0,
            "time": 0.5
          }
        },
        "pScale": {
          "init": {
            "x": 0.8,
            "y": 0.8
          }
        },
        "particleDuration": 1.5,
        "type": "DEBRIS_CIRCLE",
        "anim": "HEXA_CARD_SHOCK"
      }
    ],
    "hexaShootShock": [
      {
        "size": "L",
        "fadeIn": 0,
        "fadeOut": 0.2,
        "duration": 0.2,
        "glow": false,
        "type": "LIGHT"
      },
      {
        "numParticles": 6,
        "duration": 0.4,
        "centralAngle": 1,
        "clockwise": false,
        "random": true,
        "startDist": 4,
        "moveDist": 12,
        "moveVariance": 8,
        "keySpline": "EASE_OUT",
        "particleRotate": true,
        "normalMoveDist": 0,
        "moveRotate": 0,
        "inverse": false,
        "collision": false,
        "pScale": {
          "init": {
            "x": 0.5,
            "y": 0.5
          },
          "start": {
            "value": {
              "x": 0.2,
              "y": 0.2
            },
            "time": 0.3,
            "spline": ""
          }
        },
        "pAlpha": {
          "init": 1,
          "end": {
            "value": 0,
            "time": 0.2,
            "spline": ""
          }
        },
        "moveWithTarget": 0,
        "particleDuration": 0.8,
        "cancelable": false,
        "anim": "SHOCK_BALL_DOT2",
        "type": "OFFSET_PARTICLE_CIRCLE"
      },
      {
        "useTargetAngle": false,
        "keepAngleSync": false,
        "offset": {
          "x": 0,
          "y": 0,
          "z": 0
        },
        "pAlpha": {
          "init": 0.7,
          "start": {
            "value": 0.7,
            "spline": ""
          }
        },
        "pScale": {
          "init": {
            "x": 0,
            "y": 0
          },
          "start": {
            "value": {
              "x": 0.27,
              "y": 0.27
            },
            "spline": ""
          }
        },
        "pRotate": {
          "init": 0,
          "start": {
            "value": 0.15,
            "spline": ""
          }
        },
        "angleVary": 1,
        "moveWithTarget": 1,
        "particleDuration": 0.3,
        "cancelable": true,
        "anim": "SHOCK_BIG_HEXAGON_GUI",
        "type": "PLAY_ANIM"
      },
      {
        "time": 0.1,
        "type": "WAIT"
      },
      {
        "useTargetAngle": false,
        "keepAngleSync": false,
        "offset": {
          "x": 0,
          "y": 0,
          "z": 0
        },
        "pAlpha": {
          "init": 0.7,
          "start": {
            "value": 0.7,
            "spline": ""
          }
        },
        "pScale": {
          "init": {
            "x": 0,
            "y": 0
          },
          "start": {
            "value": {
              "x": 0.22,
              "y": 0.22
            },
            "spline": ""
          }
        },
        "pRotate": {
          "init": 0,
          "start": {
            "value": -0.15,
            "spline": ""
          }
        },
        "angleVary": 1,
        "moveWithTarget": 1,
        "particleDuration": 0.3,
        "cancelable": true,
        "anim": "SHOCK_BIG_HEXAGON_GUI",
        "type": "PLAY_ANIM"
      },
      {
        "time": 0.3,
        "type": "WAIT"
      }
    ],
    "boldPre2Hex": [
      {
        "useTargetAngle": false,
        "keepAngleSync": false,
        "pAlpha": {
          "init": 0,
          "start": {
            "value": 1,
            "spline": ""
          }
        },
        "pScale": {
          "init": {
            "x": 1.2,
            "y": 1.2
          },
          "start": {
            "value": {
              "x": 0,
              "y": 0
            },
            "spline": ""
          }
        },
        "pRotate": {
          "init": 0,
          "start": {
            "value": 0.09,
            "spline": ""
          }
        },
        "moveWithTarget": 1,
        "particleDuration": 0.35,
        "angleVary": 1,
        "anim": "SHOCK_BIG_HEXAGON",
        "type": "PLAY_ANIM"
      }
    ],
    "slowDebuff": [
      {
        "type": "LOOP_START"
      },
      {
        "color": "#1c151c",
        "noLighter": true,
        "pAlpha": {
          "init": 0.5,
          "start": {
            "value": 0.2,
            "spline": ""
          }
        },
        "pScale": {
          "init": {
            "x": 1,
            "y": 1
          },
          "start": {
            "value": {
              "x": 0.5,
              "y": 0.5
            },
            "spline": "EASE_OUT"
          }
        },
        "particleDuration": 0.5,
        "type": "COPY_SPRITE"
      },

      {
        "time": 0.1,
        "type": "WAIT"
      },
      {
        "color": "#1c151c",
        "noLighter": true,
        "pAlpha": {
          "init": 0.5,
          "start": {
            "value": 0.2,
            "spline": ""
          }
        },
        "pScale": {
          "init": {
            "x": 1,
            "y": 1
          },
          "start": {
            "value": {
              "x": 0.5,
              "y": 0.5
            },
            "spline": "EASE_OUT"
          }
        },
        "particleDuration": 0.5,
        "type": "COPY_SPRITE"
      },
      {
        "numParticles": 1,
        "duration": 0.5,
        "circular": false,
        "xScale": 1,
        "yScale": 1,
        "moveZDist": -8,
        "pAlpha": {
          "init": 1,
          "start": {
            "value": 0.5,
            "spline": ""
          }
        },
        "pRotate": {
          "init": 0
        },
        "pScale": {
          "init": {
            "x": 1.2,
            "y": 1.2
          },
          "start": {
            "value": {
              "x": 0.7,
              "y": 0.7
            },
            "spline": ""
          }
        },
        "angleVary": 0,
        "anim": "SHOCK_DOT1",
        "type": "PLAY_ANIMS_OVER_ENTITY"
      },
      {
        "time": 0.1,
        "type": "WAIT"
      },
      {
        "type": "LOOP_END"
      }
    ],
    "magnetAttract": [
      {
        "volume": 1.2,
        "global": false,
        "loop": true,
        "sound": "media/sound/puzzle/shock-magnet.ogg",
        "type": "PLAY_SOUND"
      },
      {
        "type": "LOOP_START"
      },
      {
        "duration": 0,
        "numParticles": 1,
        "flyType": "FLY_ARC",
        "inverse": true,
        "offRadiusZScale": 1,
        "rotateMoveDir": "MOVE_DIR",
        "particleDuration": 0.2,
        "anim": "SHOCK_DOT1_INV",
        "offsetRadius": 12,
        "offsetAngle": 1,
        "phaseDurations": [],
        "type": "SHOOT_HOMING_PARTICLE"
      },
      {
        "time": 0.05,
        "type": "WAIT"
      },
      {
        "duration": 0,
        "numParticles": 1,
        "flyType": "FLY_ARC",
        "inverse": true,
        "offRadiusZScale": 1,
        "rotateMoveDir": "MOVE_DIR",
        "particleDuration": 0.2,
        "anim": "SHOCK_DOT1_INV",
        "offsetRadius": 8,
        "offsetAngle": 1,
        "phaseDurations": [],
        "type": "SHOOT_HOMING_PARTICLE"
      },
      {
        "time": 0.05,
        "type": "WAIT"
      },
      {
        "type": "LOOP_END"
      },
      {
        "type": "STOP_SOUNDS"
      }
    ],
    "ghostBoldHex": [
      {
        "volume": 0.8,
        "global": false,
        "loop": false,
        "speed": 1.5,
        "sound": "media/sound/battle/heavy-thunder-2.ogg",
        "type": "PLAY_SOUND"
      },
      {
        "rumbleType": "RANDOM",
        "power": "MEDIUM",
        "speed": "FASTEST",
        "duration": 0.3,
        "fade": true,
        "type": "RUMBLE"
      },
      {
        "patternYCount": 1,
        "animFrames": [
          0,
          1,
          2,
          3,
          4
        ],
        "frameTime": 0.05,
        "shiftSpeed": 0,
        "guiSprites": true,
        "renderMode": "lighter",
        "particleDuration": 0.25,
        "pattern": {
          "src": "media/entity/effects/shock.png",
          "xCount": 5,
          "offX": 160,
          "offY": 56,
          "width": 24,
          "height": 48
        },
        "type": "LASER_SPRITE"
      },
      {
        "size": "XXL",
        "fadeIn": 0.1,
        "fadeOut": 0.1,
        "duration": 0.2,
        "glow": true,
        "type": "LIGHT"
      },
      {
        "useTargetAngle": false,
        "keepAngleSync": false,
        "pAlpha": {
          "init": 1,
          "end": {
            "value": 0,
            "time": 0.15,
            "spline": ""
          }
        },
        "pScale": {
          "init": {
            "x": 0.2,
            "y": 0.2
          },
          "start": {
            "value": {
              "x": 1.6,
              "y": 1.6
            },
            "spline": ""
          }
        },
        "moveWithTarget": 1,
        "particleDuration": 0.2,
        "anim": "CIRCLE_BIG",
        "type": "PLAY_ANIM"
      },
      {
        "numParticles": 8,
        "duration": 0,
        "centralAngle": 1,
        "startDist": 4,
        "uniformRandom": 0.9,
        "particleRotate": true,
        "moveDist": 24,
        "moveVariance": 4,
        "keySpline": "EASE_OUT",
        "moveRotate": 0,
        "inverse": false,
        "collision": false,
        "pAlpha": {
          "init": 1,
          "end": {
            "value": 0,
            "time": 0.15,
            "spline": ""
          }
        },
        "pScale": {
          "init": {
            "x": 1,
            "y": 1
          },
          "end": {
            "value": {
              "x": 0,
              "y": 1
            },
            "time": 0.1,
            "spline": ""
          }
        },
        "moveWithTarget": 1,
        "particleDuration": 0.25,
        "anim": "SHOCK_BALL_DOT2",
        "type": "OFFSET_PARTICLE_CIRCLE"
      },
      {
        "useTargetAngle": false,
        "keepAngleSync": false,
        "pAlpha": {
          "init": 0.7,
          "end": {
            "value": 0,
            "time": 0.3,
            "spline": ""
          }
        },
        "pScale": {
          "init": {
            "x": 0.3,
            "y": 0.3
          },
          "start": {
            "value": {
              "x": 1,
              "y": 1
            },
            "spline": ""
          }
        },
        "pRotate": {
          "init": 0,
          "start": {
            "value": 0.09,
            "spline": ""
          }
        },
        "moveWithTarget": 1,
        "particleDuration": 0.3,
        "angleVary": 1,
        "anim": "SHOCK_BIG_HEXAGON",
        "type": "PLAY_ANIM"
      }
    ],
    "magnetCardAura": [
      {
        "size": "XL",
        "fadeIn": 0.1,
        "fadeOut": 0.1,
        "duration": -1,
        "glow": false,
        "type": "LIGHT"
      },
      {
        "type": "LOOP_START"
      },
      {
        "volume": 1,
        "global": false,
        "loop": false,
        "variance": 0.05,
        "speed": 1,
        "sound": "media/sound/puzzle/shock-short.ogg",
        "type": "PLAY_SOUND"
      },
      {
        "radius": 24,
        "useTargetAngle": true,
        "numParticles": 1,
        "duration": 0,
        "alongY": false,
        "pAlpha": {
          "init": 1,
          "end": {
            "value": 0,
            "time": 0.05,
            "spline": ""
          }
        },
        "pScale": {
          "init": {
            "x": 0,
            "y": 0
          },
          "start": {
            "value": {
              "x": 0.7,
              "y": 0.7
            },
            "time": 0.2,
            "spline": "EASE_OUT"
          },
          "end": {
            "value": {
              "x": 0,
              "y": 0
            },
            "time": 0.2,
            "spline": "EASE_IN"
          }
        },
        "particleDuration": 0.4,
        "anim": "SHOCK_BALL_DOT2",
        "type": "PLAY_ANIM_RANGE"
      },
      {
        "useTargetAngle": true,
        "keepAngleSync": false,
        "offset": {
          "x": 0,
          "y": 0,
          "z": 0
        },
        "pAlpha": {
          "init": 0.75,
          "end": {
            "value": 0,
            "time": 0.05,
            "spline": ""
          }
        },
        "pScale": {
          "init": {
            "x": 0.85,
            "y": 0.85
          },
          "start": {
            "value": {
              "x": 0.075,
              "y": 0.075
            },
            "spline": ""
          }
        },
        "pLight": "XL",
        "particleDuration": 0.3,
        "anim": "CIRCLE_BALL_TRAIL_SHOCK",
        "type": "PLAY_ANIM"
      },
      {
        "time": 0.005,
        "type": "WAIT"
      },
      {
        "useTargetAngle": true,
        "keepAngleSync": false,
        "offset": {
          "x": 0,
          "y": 0,
          "z": 0
        },
        "pAlpha": {
          "init": 0.75,
          "end": {
            "value": 0,
            "time": 0.05,
            "spline": ""
          }
        },
        "pScale": {
          "init": {
            "x": 0.85,
            "y": 0.85
          },
          "start": {
            "value": {
              "x": 0.075,
              "y": 0.075
            },
            "spline": ""
          }
        },
        "pLight": "XL",
        "particleDuration": 0.3,
        "anim": "CIRCLE_BALL_TRAIL_SHOCK",
        "type": "PLAY_ANIM"
      },
      {
        "time": 0.005,
        "type": "WAIT"
      },
      {
        "type": "LOOP_END"
      }
    ],
    "magnetCardImpact": [
      {
        "size": "XL",
        "fadeIn": 0.1,
        "fadeOut": 0.1,
        "duration": 0.5,
        "glow": false,
        "type": "LIGHT"
      },
      {
        "color": "#f7baff",
        "maxAlpha": 0.7,
        "minAlpha": 0,
        "blinkDuration": 0.3,
        "blinkCount": 1,
        "noLighter": true,
        "type": "BLINK_COLOR"
      },
      {
        "color": "#e099ff",
        "noLighter": false,
        "pAlpha": {
          "init": 1,
          "start": {
            "value": 0,
            "spline": ""
          }
        },
        "pScale": {
          "init": {
            "x": 1,
            "y": 1
          },
          "start": {
            "value": {
              "x": 1.5,
              "y": 1.5
            },
            "spline": ""
          }
        },
        "particleDuration": 0.3,
        "moveWithTarget": 1,
        "type": "COPY_SPRITE"
      },
      {
        "useTargetAngle": false,
        "keepAngleSync": false,
        "pAlpha": {
          "init": 0.7,
          "end": {
            "value": 0,
            "time": 0.3,
            "spline": ""
          }
        },
        "pScale": {
          "init": {
            "x": 0.3,
            "y": 0.3
          },
          "start": {
            "value": {
              "x": 0.85,
              "y": 0.85
            },
            "spline": ""
          }
        },
        "pRotate": {
          "init": 0,
          "start": {
            "value": -0.09,
            "spline": ""
          }
        },
        "moveWithTarget": 1,
        "particleDuration": 0.3,
        "angleVary": 1,
        "anim": "SHOCK_BIG_HEXAGON",
        "type": "PLAY_ANIM"
      },
      {
        "numParticles": 8,
        "duration": 0.1,
        "centralAngle": 1,
        "clockwise": false,
        "random": true,
        "startDist": 12,
        "moveDist": 12,
        "moveVariance": 8,
        "keySpline": "EASE_OUT",
        "particleRotate": true,
        "normalMoveDist": 0,
        "moveRotate": 0,
        "inverse": false,
        "collision": false,
        "pScale": {
          "init": {
            "x": 0.9,
            "y": 0.9
          },
          "start": {
            "value": {
              "x": 0.4,
              "y": 0.4
            },
            "time": 0.2,
            "spline": ""
          }
        },
        "pAlpha": {
          "init": 1,
          "end": {
            "value": 0,
            "time": 0.2,
            "spline": ""
          }
        },
        "moveWithTarget": 1,
        "particleDuration": 0.5,
        "cancelable": false,
        "anim": "SHOCK_BALL_DOT2",
        "type": "OFFSET_PARTICLE_CIRCLE"
      },
      {
        "time": 0.3,
        "type": "WAIT"
      }
    ],
    "staticFieldPre": [
      {
        "volume": 0.85,
        "global": false,
        "loop": false,
        "speed": 2,
        "sound": "media/sound/battle/enemies/charge-1s.ogg",
        "type": "PLAY_SOUND"
      },
      {
        "volume": 1,
        "global": false,
        "loop": true,
        "speed": 0.8,
        "sound": "media/sound/puzzle/shock-magnet.ogg",
        "type": "PLAY_SOUND"
      },
      {
        "useTargetAngle": false,
        "keepAngleSync": false,
        "offset": {
          "x": 0,
          "y": 32,
          "z": 32
        },
        "pAlpha": {
          "init": 0.8,
          "start": {
            "value": 0.2,
            "spline": ""
          }
        },
        "pScale": {
          "init": {
            "x": 3,
            "y": 3
          },
          "start": {
            "value": {
              "x": 0.25,
              "y": 0.25
            },
            "spline": ""
          }
        },
        "pRotate": {
          "init": 0,
          "start": {
            "value": 0.5,
            "spline": "EASE_IN"
          }
        },
        "moveWithTarget": 1,
        "particleDuration": 0.5,
        "cancelable": true,
        "anim": "SHOCK_BIG_HEXAGON_GUI",
        "type": "PLAY_ANIM"
      },
      {
        "type": "LOOP_START"
      },
      {
        "numParticles": 9,
        "duration": 0.1,
        "centralAngle": 1,
        "startDist": 16,
        "random": true,
        "particleRotate": true,
        "moveDist": 96,
        "moveVariance": 24,
        "keySpline": "EASE_OUT",
        "moveRotate": 0,
        "inverse": true,
        "collision": false,
        "pAlpha": {
          "init": 1,
          "end": {
            "value": 0,
            "time": 0.15,
            "spline": ""
          }
        },
        "pScale": {
          "init": {
            "x": 0.9,
            "y": 0.9
          },
          "end": {
            "value": {
              "x": 0,
              "y": 0.5
            },
            "time": 0.1,
            "spline": ""
          }
        },
        "moveWithTarget": 1,
        "particleDuration": 0.25,
        "anim": "SHOCK_BALL_DOT2",
        "type": "OFFSET_PARTICLE_CIRCLE"
      },
      {
        "time": 0.1,
        "type": "WAIT"
      },
      {
        "type": "LOOP_END"
      }
    ],
    "staticFieldMain": [
      {
        "fadeIn": 0.2,
        "fadeOut": 0.4,
        "duration": -1,
        "intensity": 0.4,
        "type": "DARKNESS"
      },
      {
        "rumbleType": "RANDOM",
        "power": "STRONG",
        "speed": "FASTER",
        "duration": 0.3,
        "fade": true,
        "type": "RUMBLE"
      },
      {
        "volume": 1.4,
        "global": false,
        "loop": false,
        "speed": 1.5,
        "sound": "media/sound/battle/heavy-thunder-2.ogg",
        "type": "PLAY_SOUND"
      },
      {
        "volume": 1.2,
        "global": false,
        "loop": true,
        "speed": 1,
        "sound": "media/sound/puzzle/ferro-shock-loop.ogg",
        "type": "PLAY_SOUND"
      },
      {
        "color": "#471147",
        "fadeIn": 0,
        "fadeOut": 0.3,
        "duration": 0.1,
        "type": "SCREEN_FLASH"
      },
      {
        "color": "#240024",
        "fadeIn": 0,
        "fadeOut": 0.5,
        "duration": -1,
        "type": "SCREEN_FLASH"
      },
      {
        "numParticles": 1,
        "duration": 0,
        "centralAngle": 0,
        "startDist": 0,
        "random": false,
        "particleRotate": true,
        "moveDist": 0,
        "moveVariance": 0,
        "keySpline": "EASE_OUT",
        "moveRotate": 0,
        "inverse": false,
        "collision": false,
        "offset": {
          "x": 0,
          "y": 32,
          "z": 32
        },
        "pAlpha": {
          "init": 1,
          "start": {
            "value": 0,
            "spline": ""
          }
        },
        "pScale": {
          "init": {
            "x": 1.5,
            "y": 1.5
          },
          "start": {
            "value": {
              "x": 3.25,
              "y": 3.25
            },
            "spline": ""
          }
        },
        "pRotate": {
          "init": 0.25
        },
        "moveWithTarget": 1,
        "cancelable": true,
        "particleDuration": 0.4,
        "anim": "SHOCK_BIG_HEXAGON_GUI",
        "type": "OFFSET_PARTICLE_CIRCLE"
      },
      {
        "useTargetAngle": false,
        "keepAngleSync": false,
        "pAlpha": {
          "init": 0.5,
          "end": {
            "value": 0,
            "time": 0.15,
            "spline": ""
          }
        },
        "pScale": {
          "init": {
            "x": 0.2,
            "y": 0.2
          },
          "start": {
            "value": {
              "x": 1,
              "y": 1
            },
            "time": 0.1,
            "spline": ""
          },
          "end": {
            "value": {
              "x": 0.2,
              "y": 0.2
            },
            "time": 0.1,
            "spline": ""
          }
        },
        "moveWithTarget": 1,
        "particleDuration": -1,
        "anim": "CIRCLE_BIG_BACK",
        "type": "PLAY_ANIM"
      },
      {
        "rumbleType": "RANDOM",
        "power": "WEAK",
        "speed": "FASTER",
        "duration": -1,
        "fade": false,
        "type": "RUMBLE"
      },
      {
        "size": "XXL",
        "fadeIn": 0.1,
        "fadeOut": 0.1,
        "duration": -1,
        "glow": false,
        "type": "LIGHT"
      },
      {
        "color": "#aa22ff",
        "maxAlpha": 1,
        "minAlpha": 0.5,
        "blinkDuration": 0.1,
        "blinkCount": -1,
        "noLighter": true,
        "type": "BLINK_COLOR"
      },
      {
        "type": "LOOP_START"
      },
      {
        "volume": 0.7,
        "global": false,
        "loop": false,
        "speed": 1.4,
        "sound": "media/sound/puzzle/shock-snap.ogg",
        "type": "PLAY_SOUND"
      },
      {
        "numParticles": 1,
        "duration": 0,
        "centralAngle": 0,
        "startDist": 0,
        "random": false,
        "particleRotate": true,
        "moveDist": 0,
        "moveVariance": 0,
        "keySpline": "EASE_OUT",
        "moveRotate": 0,
        "inverse": false,
        "collision": false,
        "pAlpha": {
          "init": 1,
          "start": {
            "value": 0,
            "spline": ""
          }
        },
        "pScale": {
          "init": {
            "x": 1.5,
            "y": 1.5
          },
          "start": {
            "value": {
              "x": 2,
              "y": 2
            },
            "spline": ""
          }
        },
        "pRotate": {
          "init": 0.25
        },
        "moveWithTarget": 1,
        "cancelable": true,
        "particleDuration": 0.2,
        "anim": "SHOCK_BIG_HEXAGON_GUI",
        "type": "OFFSET_PARTICLE_CIRCLE"
      },
      {
        "numParticles": 6,
        "duration": 0.1,
        "centralAngle": 1,
        "startDist": 4,
        "random": true,
        "particleRotate": true,
        "moveDist": 48,
        "moveVariance": 4,
        "keySpline": "EASE_OUT",
        "moveRotate": 0,
        "inverse": false,
        "collision": false,
        "pAlpha": {
          "init": 1,
          "end": {
            "value": 0,
            "time": 0.15,
            "spline": ""
          }
        },
        "pScale": {
          "init": {
            "x": 0.5,
            "y": 0.5
          },
          "start": {
            "value": {
              "x": 0,
              "y": 0
            },
            "spline": ""
          }
        },
        "moveWithTarget": 1,
        "particleDuration": 0.25,
        "anim": "CIRCLE_BIG",
        "type": "OFFSET_PARTICLE_CIRCLE"
      },
      {
        "numParticles": 9,
        "duration": 0.1,
        "centralAngle": 1,
        "startDist": 4,
        "random": true,
        "particleRotate": true,
        "moveDist": 64,
        "moveVariance": 4,
        "keySpline": "EASE_OUT",
        "moveRotate": 0,
        "inverse": false,
        "collision": false,
        "pAlpha": {
          "init": 1,
          "end": {
            "value": 0,
            "time": 0.15,
            "spline": ""
          }
        },
        "pScale": {
          "init": {
            "x": 1,
            "y": 1
          },
          "end": {
            "value": {
              "x": 0,
              "y": 1
            },
            "time": 0.1,
            "spline": ""
          }
        },
        "moveWithTarget": 1,
        "particleDuration": 0.25,
        "anim": "SHOCK_BALL_DOT2",
        "type": "OFFSET_PARTICLE_CIRCLE"
      },
      {
        "time": 0.1,
        "type": "WAIT"
      },
      {
        "type": "LOOP_END"
      }
    ],
    "staticFieldEnd": [
      {
        "rumbleType": "RANDOM",
        "power": "STRONGER",
        "speed": "FASTEST",
        "duration": 0.5,
        "fade": true,
        "type": "RUMBLE"
      },
      {
        "volume": 1,
        "global": false,
        "loop": false,
        "speed": 1.2,
        "sound": "media/sound/battle/heavy-thunder-2.ogg",
        "type": "PLAY_SOUND"
      },
      {
        "useTargetAngle": false,
        "keepAngleSync": false,
        "pAlpha": {
          "init": 0.5,
          "end": {
            "value": 0,
            "time": 0.15,
            "spline": ""
          }
        },
        "pScale": {
          "init": {
            "x": 0.2,
            "y": 0.2
          },
          "start": {
            "value": {
              "x": 4,
              "y": 4
            },
            "spline": ""
          }
        },
        "moveWithTarget": 1,
        "particleDuration": 0.3,
        "anim": "CIRCLE_BIG",
        "type": "PLAY_ANIM"
      },
      {
        "numParticles": 24,
        "duration": 0,
        "centralAngle": 1,
        "startDist": 4,
        "random": true,
        "particleRotate": true,
        "moveDist": 128,
        "moveVariance": 64,
        "keySpline": "EASE_OUT",
        "moveRotate": 0,
        "inverse": false,
        "collision": false,
        "pAlpha": {
          "init": 1,
          "end": {
            "value": 0,
            "time": 0.15,
            "spline": ""
          }
        },
        "pScale": {
          "init": {
            "x": 1,
            "y": 1
          },
          "end": {
            "value": {
              "x": 0,
              "y": 1
            },
            "time": 0.1,
            "spline": ""
          }
        },
        "moveWithTarget": 1,
        "particleDuration": 0.45,
        "anim": "SHOCK_BALL_DOT2",
        "type": "OFFSET_PARTICLE_CIRCLE"
      },
      {
        "color": "#471147",
        "fadeIn": 0,
        "fadeOut": 0.3,
        "duration": 0.1,
        "type": "SCREEN_FLASH"
      },
      {
        "useTargetAngle": false,
        "keepAngleSync": false,
        "offset": {
          "x": 0,
          "y": 32,
          "z": 32
        },
        "pAlpha": {
          "init": 1,
          "start": {
            "value": 0,
            "spline": ""
          }
        },
        "pScale": {
          "init": {
            "x": 0,
            "y": 0
          },
          "start": {
            "value": {
              "x": 3.5,
              "y": 3.5
            },
            "spline": ""
          }
        },
        "moveWithTarget": 1,
        "particleDuration": 0.25,
        "anim": "SHOCK_BIG_HEXAGON_GUI",
        "type": "PLAY_ANIM"
      }
    ],
    "staticFieldUserFX": [
      {
        "volume": 1,
        "global": false,
        "loop": false,
        "speed": 1,
        "sound": "media/sound/puzzle/shock-short.ogg",
        "type": "PLAY_SOUND"
      },
      {
        "size": "XL",
        "fadeIn": 0.1,
        "fadeOut": 0.1,
        "duration": -1,
        "glow": true,
        "type": "LIGHT"
      },
      {
        "color": "#d690fc",
        "maxAlpha": 0.5,
        "minAlpha": 0.7,
        "blinkDuration": 0.1,
        "blinkCount": -1,
        "noLighter": false,
        "type": "BLINK_COLOR"
      },
      {
        "color": "#c252ff",
        "noLighter": false,
        "pAlpha": {
          "init": 1,
          "start": {
            "value": 0,
            "spline": ""
          }
        },
        "pScale": {
          "init": {
            "x": 1,
            "y": 1
          },
          "start": {
            "value": {
              "x": 3.5,
              "y": 3.5
            },
            "spline": ""
          }
        },
        "particleDuration": 0.4,
        "cancelable": false,
        "type": "COPY_SPRITE"
      },
      {
        "type": "LOOP_START"
      },
      {
        "volume": 0.3,
        "global": false,
        "loop": false,
        "variance": 0.1,
        "speed": 0.9,
        "sound": "media/sound/puzzle/shock-snap.ogg",
        "type": "PLAY_SOUND"
      },
      {
        "numParticles": 3,
        "duration": 0.3,
        "circular": false,
        "xScale": 0.7,
        "yScale": 0.7,
        "offset": {
          "x": 0,
          "y": 32,
          "z": 32
        },
        "pRotate": {
          "init": 0.25
        },
        "anim": "SPARK4",
        "angleVary": 1,
        "type": "PLAY_ANIMS_OVER_ENTITY"
      },
      {
        "color": "#eb99ff",
        "noLighter": false,
        "pAlpha": {
          "init": 0.8,
          "start": {
            "value": 0,
            "spline": ""
          }
        },
        "pScale": {
          "init": {
            "x": 1,
            "y": 1
          },
          "start": {
            "value": {
              "x": 1.5,
              "y": 1.5
            },
            "spline": ""
          }
        },
        "particleDuration": 0.2,
        "type": "COPY_SPRITE"
      },
      {
        "time": 0.1,
        "type": "WAIT"
      },
      {
        "type": "LOOP_END"
      }
    ],
    "staticDischargePre": [
      {
        "volume": 1.5,
        "global": false,
        "loop": false,
        "variance": 0.1,
        "speed": 1.1,
        "type": "PLAY_SOUND",
        "sound": "media/sound/battle/shock-add-2.ogg"
      },
      {
        "volume": 1,
        "global": false,
        "loop": true,
        "speed": 0.8,
        "sound": "media/sound/puzzle/shock-magnet.ogg",
        "type": "PLAY_SOUND"
      },
      {
        "useTargetAngle": false,
        "keepAngleSync": false,
        "offset": {
          "x": 0,
          "y": 32,
          "z": 32
        },
        "pAlpha": {
          "init": 0,
          "start": {
            "value": 0.8,
            "spline": ""
          }
        },
        "pScale": {
          "init": {
            "x": 2.25,
            "y": 2.25
          },
          "start": {
            "value": {
              "x": 0.8,
              "y": 0.8
            },
            "spline": ""
          }
        },
        "pRotate": {
          "init": 0,
          "start": {
            "value": 0.25,
            "spline": "EASE_OUT"
          }
        },
        "moveWithTarget": 1,
        "particleDuration": 0.15,
        "cancelable": true,
        "anim": "SHOCK_BIG_HEXAGON_GUI",
        "type": "PLAY_ANIM"
      },
      {
        "type": "LOOP_START"
      },
      {
        "numParticles": 5,
        "duration": 0.1,
        "centralAngle": 1,
        "startDist": 8,
        "random": true,
        "particleRotate": true,
        "moveDist": 48,
        "moveVariance": 12,
        "keySpline": "EASE_OUT",
        "moveRotate": 0,
        "inverse": true,
        "collision": false,
        "pAlpha": {
          "init": 1,
          "end": {
            "value": 0,
            "time": 0.15,
            "spline": ""
          }
        },
        "pScale": {
          "init": {
            "x": 0.5,
            "y": 0.5
          },
          "end": {
            "value": {
              "x": 0,
              "y": 0.5
            },
            "time": 0.1,
            "spline": ""
          }
        },
        "moveWithTarget": 1,
        "particleDuration": 0.25,
        "anim": "SHOCK_BALL_DOT2",
        "type": "OFFSET_PARTICLE_CIRCLE"
      },
      {
        "time": 0.05,
        "type": "WAIT"
      },
      {
        "type": "LOOP_END"
      }
    ],
    "staticDischargeMain": [
      {
        "fadeIn": 0.2,
        "fadeOut": 0.4,
        "duration": -1,
        "intensity": 0.2,
        "type": "DARKNESS"
      },
      {
        "rumbleType": "RANDOM",
        "power": "MEDIUM",
        "speed": "FASTER",
        "duration": 0.3,
        "fade": true,
        "type": "RUMBLE"
      },
      {
        "volume": 0.8,
        "global": false,
        "loop": false,
        "speed": 1.2,
        "sound": "media/sound/battle/heavy-thunder-2.ogg",
        "type": "PLAY_SOUND"
      },
      {
        "volume": 1.2,
        "global": false,
        "loop": true,
        "speed": 1,
        "sound": "media/sound/puzzle/ferro-shock-loop.ogg",
        "type": "PLAY_SOUND"
      },
      {
        "numParticles": 1,
        "duration": 0,
        "centralAngle": 0,
        "startDist": 0,
        "random": false,
        "particleRotate": true,
        "moveDist": 0,
        "moveVariance": 0,
        "keySpline": "EASE_OUT",
        "moveRotate": 0,
        "inverse": false,
        "collision": false,
        "offset": {
          "x": 0,
          "y": 32,
          "z": 32
        },
        "pAlpha": {
          "init": 0.5,
          "start": {
            "value": 0,
            "spline": ""
          }
        },
        "pScale": {
          "init": {
            "x": 0.8,
            "y": 0.8
          },
          "start": {
            "value": {
              "x": 2.25,
              "y": 2.25
            },
            "spline": ""
          }
        },
        "pRotate": {
          "init": 0.25
        },
        "moveWithTarget": 1,
        "cancelable": true,
        "particleDuration": 0.4,
        "anim": "SHOCK_BIG_HEXAGON_GUI",
        "type": "OFFSET_PARTICLE_CIRCLE"
      },
      {
        "useTargetAngle": false,
        "keepAngleSync": false,
        "pAlpha": {
          "init": 0.5,
          "end": {
            "value": 0,
            "time": 0.15,
            "spline": ""
          }
        },
        "pScale": {
          "init": {
            "x": 0.1,
            "y": 0.1
          },
          "start": {
            "value": {
              "x": 0.5,
              "y": 0.5
            },
            "time": 0.1,
            "spline": ""
          },
          "end": {
            "value": {
              "x": 0.1,
              "y": 0.1
            },
            "time": 0.1,
            "spline": ""
          }
        },
        "moveWithTarget": 1,
        "particleDuration": -1,
        "anim": "CIRCLE_BIG_BACK",
        "type": "PLAY_ANIM"
      },
      {
        "rumbleType": "RANDOM",
        "power": "WEAK",
        "speed": "FASTER",
        "duration": -1,
        "fade": false,
        "type": "RUMBLE"
      },
      {
        "size": "XXL",
        "fadeIn": 0.1,
        "fadeOut": 0.1,
        "duration": -1,
        "glow": false,
        "type": "LIGHT"
      },
      {
        "color": "#aa22ff",
        "maxAlpha": 1,
        "minAlpha": 0.5,
        "blinkDuration": 0.1,
        "blinkCount": -1,
        "noLighter": true,
        "type": "BLINK_COLOR"
      },
      {
        "type": "LOOP_START"
      },
      {
        "volume": 0.7,
        "global": false,
        "loop": false,
        "speed": 1.4,
        "sound": "media/sound/puzzle/shock-snap.ogg",
        "type": "PLAY_SOUND"
      },
      {
        "numParticles": 1,
        "duration": 0,
        "centralAngle": 0,
        "startDist": 0,
        "random": false,
        "particleRotate": true,
        "moveDist": 0,
        "moveVariance": 0,
        "keySpline": "EASE_OUT",
        "moveRotate": 0,
        "inverse": false,
        "collision": false,
        "pAlpha": {
          "init": 1,
          "start": {
            "value": 0,
            "spline": ""
          }
        },
        "pScale": {
          "init": {
            "x": 0.7,
            "y": 0.7
          },
          "start": {
            "value": {
              "x": 1,
              "y": 1
            },
            "spline": ""
          }
        },
        "pRotate": {
          "init": 0.25
        },
        "moveWithTarget": 1,
        "cancelable": true,
        "particleDuration": 0.2,
        "anim": "SHOCK_BIG_HEXAGON_GUI",
        "type": "OFFSET_PARTICLE_CIRCLE"
      },
      {
        "numParticles": 6,
        "duration": 0.1,
        "centralAngle": 1,
        "startDist": 4,
        "random": true,
        "particleRotate": true,
        "moveDist": 24,
        "moveVariance": 4,
        "keySpline": "EASE_OUT",
        "moveRotate": 0,
        "inverse": false,
        "collision": false,
        "pAlpha": {
          "init": 1,
          "end": {
            "value": 0,
            "time": 0.15,
            "spline": ""
          }
        },
        "pScale": {
          "init": {
            "x": 0.25,
            "y": 0.25
          },
          "start": {
            "value": {
              "x": 0,
              "y": 0
            },
            "spline": ""
          }
        },
        "moveWithTarget": 1,
        "particleDuration": 0.25,
        "anim": "CIRCLE_BIG",
        "type": "OFFSET_PARTICLE_CIRCLE"
      },
      {
        "numParticles": 9,
        "duration": 0.1,
        "centralAngle": 1,
        "startDist": 4,
        "random": true,
        "particleRotate": true,
        "moveDist": 32,
        "moveVariance": 4,
        "keySpline": "EASE_OUT",
        "moveRotate": 0,
        "inverse": false,
        "collision": false,
        "pAlpha": {
          "init": 1,
          "end": {
            "value": 0,
            "time": 0.15,
            "spline": ""
          }
        },
        "pScale": {
          "init": {
            "x": 0.5,
            "y": 0.5
          },
          "end": {
            "value": {
              "x": 0,
              "y": 0.5
            },
            "time": 0.1,
            "spline": ""
          }
        },
        "moveWithTarget": 1,
        "particleDuration": 0.25,
        "anim": "SHOCK_BALL_DOT2",
        "type": "OFFSET_PARTICLE_CIRCLE"
      },
      {
        "time": 0.1,
        "type": "WAIT"
      },
      {
        "type": "LOOP_END"
      }
    ],
    "staticDischargeBold": [
      {
        "volume": 0.8,
        "global": false,
        "loop": false,
        "speed": 1.5,
        "sound": "media/sound/battle/heavy-thunder-2.ogg",
        "type": "PLAY_SOUND"
      },
      {
        "rumbleType": "RANDOM",
        "power": "MEDIUM",
        "speed": "FASTEST",
        "duration": 0.3,
        "fade": true,
        "type": "RUMBLE"
      },
      {
        "patternYCount": 1,
        "animFrames": [
          0,
          1,
          2,
          3,
          4
        ],
        "frameTime": 0.05,
        "shiftSpeed": 0,
        "guiSprites": true,
        "renderMode": "lighter",
        "particleDuration": 0.25,
        "pattern": {
          "src": "media/entity/effects/shock.png",
          "xCount": 5,
          "offX": 160,
          "offY": 56,
          "width": 24,
          "height": 48
        },
        "type": "LASER_SPRITE"
      },
      {
        "size": "XXL",
        "fadeIn": 0.1,
        "fadeOut": 0.1,
        "duration": 0.2,
        "glow": true,
        "type": "LIGHT"
      },
      {
        "useTargetAngle": false,
        "keepAngleSync": false,
        "pAlpha": {
          "init": 1,
          "end": {
            "value": 0,
            "time": 0.15,
            "spline": ""
          }
        },
        "pScale": {
          "init": {
            "x": 0.2,
            "y": 0.2
          },
          "start": {
            "value": {
              "x": 1.6,
              "y": 1.6
            },
            "spline": ""
          }
        },
        "moveWithTarget": 1,
        "particleDuration": 0.2,
        "anim": "CIRCLE_BIG",
        "type": "PLAY_ANIM"
      },
      {
        "numParticles": 12,
        "duration": 0,
        "centralAngle": 1,
        "startDist": 4,
        "uniformRandom": 0.9,
        "particleRotate": true,
        "moveDist": 50,
        "moveVariance": 16,
        "keySpline": "EASE_OUT",
        "moveRotate": 0,
        "inverse": false,
        "collision": false,
        "pAlpha": {
          "init": 1,
          "end": {
            "value": 0,
            "time": 0.15,
            "spline": ""
          }
        },
        "pScale": {
          "init": {
            "x": 1,
            "y": 1
          },
          "end": {
            "value": {
              "x": 0,
              "y": 1
            },
            "time": 0.1,
            "spline": ""
          }
        },
        "moveWithTarget": 1,
        "particleDuration": 0.25,
        "anim": "SHOCK_BALL_DOT2",
        "type": "OFFSET_PARTICLE_CIRCLE"
      },
      {
        "useTargetAngle": false,
        "keepAngleSync": false,
        "pAlpha": {
          "init": 1,
          "end": {
            "value": 0,
            "time": 0.3,
            "spline": ""
          }
        },
        "pScale": {
          "init": {
            "x": 0.8,
            "y": 0.8
          },
          "start": {
            "value": {
              "x": 1.75,
              "y": 1.75
            },
            "spline": ""
          }
        },
        "pRotate": {
          "init": 0.25,
          "start": {
            "value": 0.12,
            "spline": "EASE_IN"
          }
        },
        "moveWithTarget": 1,
        "particleDuration": 0.2,
        "angleVary": 1,
        "anim": "SHOCK_BIG_HEXAGON_GUI",
        "type": "PLAY_ANIM"
      }
    ],
    "magnetCardSparkle": [
      {
        "size": "L",
        "fadeIn": 0,
        "fadeOut": 0.4,
        "duration": 0.3,
        "glow": true,
        "type": "LIGHT"
      },
      {
        "alpha": 1,
        "duration": 0,
        "type": "CHANGE_ALPHA"
      },
      {
        "color": "white",
        "alpha": 1,
        "fadeIn": 0,
        "fadeOut": 0.3,
        "duration": 0.2,
        "noLighter": false,
        "type": "FADE_COLOR"
      },
      {
        "numParticles": 3,
        "duration": 0,
        "centralAngle": 1,
        "startDist": 8,
        "uniformRandom": 0.1,
        "particleRotate": true,
        "moveDist": 42,
        "keySpline": "EASE_OUT",
        "moveRotate": 0.1,
        "rotateWithTime": true,
        "inverse": false,
        "collision": false,
        "pAlpha": {
          "init": 0.8
        },
        "pScale": {
          "init": {
            "x": 0.5,
            "y": 1
          },
          "start": {
            "value": {
              "x": 0,
              "y": 4
            },
            "spline": "EASE_OUT"
          }
        },
        "moveWithTarget": 1,
        "particleDuration": -2,
        "anim": "CIRCLE_SMALL_SHOCK",
        "type": "OFFSET_PARTICLE_CIRCLE"
      },
      {
        "numParticles": 3,
        "duration": 0,
        "centralAngle": 1,
        "startDist": 8,
        "uniformRandom": 0.1,
        "particleRotate": true,
        "moveDist": 24,
        "keySpline": "EASE_OUT",
        "moveRotate": -0.1,
        "rotateWithTime": true,
        "inverse": false,
        "collision": false,
        "pAlpha": {
          "init": 0.8
        },
        "pScale": {
          "init": {
            "x": 0.25,
            "y": 0.5
          },
          "start": {
            "value": {
              "x": 0,
              "y": 2.5
            },
            "spline": "EASE_OUT"
          }
        },
        "moveWithTarget": 1,
        "particleDuration": -2,
        "anim": "CIRCLE_SMALL_SHOCK",
        "type": "OFFSET_PARTICLE_CIRCLE"
      },
      {
        "useTargetAngle": true,
        "keepAngleSync": false,
        "offset": {
          "x": 0,
          "y": 128,
          "z": 128
        },
        "pAlpha": {
          "init": 0.5,
          "start": {
            "value": 0,
            "spline": ""
          }
        },
        "pRotate": {
          "init": 0.5
        },
        "pScale": {
          "init": {
            "x": 0,
            "y": 0
          },
          "start": {
            "value": {
              "x": 0.8,
              "y": 0.8
            },
            "spline": "EASE_OUT"
          }
        },
        "particleDuration": 0.6,
        "moveWithTarget": 1,
        "anim": "SHOCK_BIG_HEXAGON",
        "type": "PLAY_ANIM"
      },
      {
        "numParticles": 8,
        "duration": 0.3,
        "centralAngle": 1,
        "clockwise": false,
        "random": true,
        "startDist": 4,
        "moveDist": 16,
        "moveVariance": 8,
        "keySpline": "EASE_OUT",
        "particleRotate": true,
        "normalMoveDist": 0,
        "moveRotate": 0,
        "inverse": false,
        "collision": false,
        "pAlpha": {
          "init": 1
        },
        "pScale": {
          "init": {
            "x": 1,
            "y": 1
          },
          "start": {
            "value": {
              "x": 0.2,
              "y": 0.2
            },
            "time": 0.3,
            "spline": ""
          }
        },
        "moveWithTarget": 0,
        "particleDuration": 0.3,
        "cancelable": false,
        "anim": "SHOCK_BALL_DOT2",
        "type": "OFFSET_PARTICLE_CIRCLE"
      }
    ]
  }
}